MANIFEST.in
README.md
setup.cfg
setup.py
pyriemann/__init__.py
pyriemann/channelselection.py
pyriemann/classification.py
pyriemann/clustering.py
pyriemann/embedding.py
pyriemann/estimation.py
pyriemann/spatialfilters.py
pyriemann/stats.py
pyriemann/tangentspace.py
pyriemann/utils/__init__.py
pyriemann/utils/ajd.py
pyriemann/utils/base.py
pyriemann/utils/covariance.py
pyriemann/utils/distance.py
pyriemann/utils/geodesic.py
pyriemann/utils/mean.py
pyriemann/utils/tangentspace.py
pyriemann/utils/utils.py
pyriemann_slim.egg-info/PKG-INFO
pyriemann_slim.egg-info/SOURCES.txt
pyriemann_slim.egg-info/dependency_links.txt
pyriemann_slim.egg-info/not-zip-safe
pyriemann_slim.egg-info/requires.txt
pyriemann_slim.egg-info/top_level.txt