Metadata-Version: 1.0
Name: pyriemann-slim
Version: 0.3.2
Summary: Riemannian Geometry for python for embedded systems
Home-page: UNKNOWN
Author: Alexandre Barachant
Author-email: alexandre.barachant@gmail.com
License: BSD (3-clause)
Platform: UNKNOWN
